XinrenleiMima/Dockerfile
XinrenleiMima/README.md
XinrenleiMima/__init__.py
XinrenleiMima/__main__.py
XinrenleiMima/file.epub
XinrenleiMima/index.html
XinrenleiMima/css/__init__.py
XinrenleiMima/css/annotations.css
XinrenleiMima/css/main.css
XinrenleiMima/css/normalize.css
XinrenleiMima/css/popup.css
XinrenleiMima/font/__init__.py
XinrenleiMima/font/fontello.eot
XinrenleiMima/font/fontello.svg
XinrenleiMima/font/fontello.ttf
XinrenleiMima/font/fontello.woff
XinrenleiMima/img/__init__.py
XinrenleiMima/img/annotator-glyph-sprite.png
XinrenleiMima/img/annotator-icon-sprite.png
XinrenleiMima/img/apple-touch-icon.png
XinrenleiMima/img/cancelfullscreen.png
XinrenleiMima/img/close.png
XinrenleiMima/img/fullscreen.png
XinrenleiMima/img/loader.gif
XinrenleiMima/img/menu-icon.png
XinrenleiMima/img/save.png
XinrenleiMima/img/saved.png
XinrenleiMima/img/settings-s.png
XinrenleiMima/img/settings.png
XinrenleiMima/img/star.png
XinrenleiMima/js/__init__.py
XinrenleiMima/js/epub.js
XinrenleiMima/js/epub.min.js
XinrenleiMima/js/epub.min.map
XinrenleiMima/js/hooks.min.js
XinrenleiMima/js/hooks.min.map
XinrenleiMima/js/reader.js
XinrenleiMima/js/reader.js.map
XinrenleiMima/js/reader.min.js
XinrenleiMima/js/reader.min.map
XinrenleiMima/js/hooks/__init__.py
XinrenleiMima/js/hooks/extensions/__init__.py
XinrenleiMima/js/hooks/extensions/highlight.js
XinrenleiMima/js/libs/__init__.py
XinrenleiMima/js/libs/jquery.min.js
XinrenleiMima/js/libs/localforage.min.js
XinrenleiMima/js/libs/screenfull.js
XinrenleiMima/js/libs/screenfull.min.js
XinrenleiMima/js/libs/zip.min.js
XinrenleiMima/js/plugins/__init__.py
XinrenleiMima/js/plugins/hypothesis.js
XinrenleiMima/js/plugins/search.js
xinrenlei_mima-2022.10.7.1.dist-info/METADATA
xinrenlei_mima-2022.10.7.1.dist-info/WHEEL
xinrenlei_mima-2022.10.7.1.dist-info/entry_points.txt
xinrenlei_mima-2022.10.7.1.dist-info/top_level.txt
xinrenlei_mima-2022.10.7.1.dist-info/RECORD
